pkgver/__init__.py
src/__init__.py
src/extractor.py
src/database/__init__.py
src/database/dynamodb.py
src/resources/__init__.py
src/resources/custom_logger_formatter.py
src/resources/ldap.py
src/resources/service.py
src/utils/__init__.py
src/utils/constants.py
src/utils/misc.py
scora_ldap_extractor-1.3.0.dist-info/LICENSE
scora_ldap_extractor-1.3.0.dist-info/METADATA
scora_ldap_extractor-1.3.0.dist-info/WHEEL
scora_ldap_extractor-1.3.0.dist-info/top_level.txt
scora_ldap_extractor-1.3.0.dist-info/zip-safe
scora_ldap_extractor-1.3.0.dist-info/RECORD
