Metadata-Version: 2.1
Name: scora-ldap-extractor
Version: 1.3.0
Summary: Scora Ldap Extractor
Home-page: https://github.com/oncase/scora-ldap-extractor
Author: Oncase
Author-email: contato@oncase.com.br
Maintainer: Guilherme Morone
Maintainer-email: guilherme.morone@oncase.com.br
License: MIT
Keywords: scora
Classifier: Intended Audience :: Developers
Classifier: Natural Language :: English
Classifier: Programming Language :: Python :: 3.11
Requires-Python: >=3.8
License-File: LICENSE
Requires-Dist: ldap3 (>=2.9.1)
Requires-Dist: boto3 (>=1.26.57)
Requires-Dist: python-dotenv (>=0.21.1)
Requires-Dist: environs (>=9.5.0)
Requires-Dist: numpy (>=1.24.1)
